ipfs_accelerate_py/__init__.py
ipfs_accelerate_py/config.py
ipfs_accelerate_py/ipfs_accelerate.py
ipfs_accelerate_py/ipfs_multiformats.py
ipfs_accelerate_py/test_backend.py
ipfs_accelerate_py/test_ipfs_accelerate.py
ipfs_accelerate_py/config/__init__.py
ipfs_accelerate_py/config/config.py
ipfs_accelerate_py/container_backends/__init__.py
ipfs_accelerate_py/container_backends/backends.py
ipfs_accelerate_py/container_backends/test_backends.py
ipfs_accelerate_py/install_depends/__init__.py
ipfs_accelerate_py/install_depends/install_depends.py
ipfs_accelerate_py/worker/__init__.py
ipfs_accelerate_py/worker/ipfs_multiformats.py
ipfs_accelerate_py/worker/openvino_utils.py
ipfs_accelerate_py/worker/worker.py
ipfs_accelerate_py/worker/skillset/__init__.py
ipfs_accelerate_py/worker/skillset/chat_format.py
ipfs_accelerate_py/worker/skillset/clip_retrieval.py
ipfs_accelerate_py/worker/skillset/coqui_tts_kit.py
ipfs_accelerate_py/worker/skillset/default.py
ipfs_accelerate_py/worker/skillset/hf_clip.py
ipfs_accelerate_py/worker/skillset/hf_embed bak.py
ipfs_accelerate_py/worker/skillset/hf_embed.py
ipfs_accelerate_py/worker/skillset/hf_faster_whisper.py
ipfs_accelerate_py/worker/skillset/hf_llava.py
ipfs_accelerate_py/worker/skillset/hf_lm.py
ipfs_accelerate_py/worker/skillset/hf_lm_bak.py
ipfs_accelerate_py/worker/skillset/hf_t5.py
ipfs_accelerate_py/worker/skillset/hf_wav2vec.py
ipfs_accelerate_py/worker/skillset/llama_cpp_kit.py
ipfs_accelerate_py/worker/skillset/openai_api.py
ipfs_accelerate_py/worker/skillset/s3_kit.py
ipfs_accelerate_py-0.0.42.dist-info/LICENSE
ipfs_accelerate_py-0.0.42.dist-info/METADATA
ipfs_accelerate_py-0.0.42.dist-info/WHEEL
ipfs_accelerate_py-0.0.42.dist-info/top_level.txt
ipfs_accelerate_py-0.0.42.dist-info/RECORD
